tmxiterparse/__init__.py
tmxiterparse/tmxparser.py
tmxiterparse-0.1.2.dist-info/LICENSE
tmxiterparse-0.1.2.dist-info/WHEEL
tmxiterparse-0.1.2.dist-info/METADATA
tmxiterparse-0.1.2.dist-info/RECORD
